imessage/__init__.py
imessage/imessage.py
imessage-0.0.3.dist-info/LICENSE
imessage-0.0.3.dist-info/METADATA
imessage-0.0.3.dist-info/WHEEL
imessage-0.0.3.dist-info/top_level.txt
imessage-0.0.3.dist-info/RECORD
