Metadata-Version: 2.1
Name: imessage
Version: 0.0.3
Summary: A small package to export an iMessage database as a pandas dataframe
Home-page: https://github.com/willmmoses/imessage
Author: Will Mason Moses
Author-email: author@example.com
License: UNKNOWN
Project-URL: Bug Tracker, https://github.com/willmmoses/imessage/issues
Platform: UNKNOWN
Classifier: Programming Language :: Python :: 3
Classifier: License :: OSI Approved :: MIT License
Classifier: Operating System :: OS Independent
Requires-Python: >=3.6
License-File: LICENSE
